dhcptool/__init__.py
dhcptool/base_dhcp_pkt.py
dhcptool/code_call_exec.py
dhcptool/dhcp4_controller.py
dhcptool/dhcp6_controller.py
dhcptool/dhcp_pkt_v4.py
dhcptool/dhcp_pkt_v6.py
dhcptool/dhcptool.yaml
dhcptool/env_args.py
dhcptool/extend_tools_controller.py
dhcptool/Logings.py
dhcptool/main.py
dhcptool/options.py
dhcptool/tools.py
dhcptool-2025.9.10.2.dist-info/entry_points.txt
dhcptool-2025.9.10.2.dist-info/METADATA
dhcptool-2025.9.10.2.dist-info/WHEEL
dhcptool-2025.9.10.2.dist-info/RECORD
