Metadata-Version: 2.3
Name: dhcptool
Version: 2025.9.10.2
Summary: 优化发包逻辑，以及发包效率
Author: mf.liang
Author-email: mf.liang@outlook.com
Requires-Python: >=3.6.8,<4.0.0
Classifier: Programming Language :: Python :: 3
Classifier: Programming Language :: Python :: 3.7
Classifier: Programming Language :: Python :: 3.8
Classifier: Programming Language :: Python :: 3.9
Classifier: Programming Language :: Python :: 3.10
Classifier: Programming Language :: Python :: 3.11
Classifier: Programming Language :: Python :: 3.12
Classifier: Programming Language :: Python :: 3.13
Requires-Dist: pyyaml (>=6.0.1,<7.0.0)
Requires-Dist: scapy (>=2.5.0,<3.0.0)
